_liblip.abi3.so
liblip.py
liblip-0.91.dist-info/.DS_Store
liblip-0.91.dist-info/LICENSE.txt
liblip-0.91.dist-info/METADATA
liblip-0.91.dist-info/WHEEL
liblip-0.91.dist-info/top_level.txt
liblip-0.91.dist-info/RECORD
