Metadata-Version: 2.1
Name: liblip
Version: 0.91
Summary: Library for multivariate scattered data interpolation
Home-page: UNKNOWN
Author: Gleb Beliakov, Norbert Henseler
Author-email: gleb.beliakov@deakin.edu.au, norbert.henseler@deakin.edu.au
License: UNKNOWN
Platform: UNKNOWN
License-File: LICENSE.txt
Requires-Dist: cffi (>=1.0.0)
